packaging_demo/__init__.py
packaging_demo/colorized_demo.py
packaging_demo/my_file.py
packaging_demo/my_other_file.py
packaging_demo/states_info.py
packaging_demo/my_folder/__init__.py
packaging_demo/my_folder/my_nested_file.py
packaging_demo/my_folder/sub_package/__init__.py
packaging_demo/my_folder/sub_package/some_deeply_nested_file.py
packaging_demo_Dalia-0.0.8.dist-info/METADATA
packaging_demo_Dalia-0.0.8.dist-info/WHEEL
packaging_demo_Dalia-0.0.8.dist-info/top_level.txt
packaging_demo_Dalia-0.0.8.dist-info/RECORD
